barrack/Medic.py
barrack/__init__.py
mjade_ex-0.0.2.dist-info/LICENSE
mjade_ex-0.0.2.dist-info/METADATA
mjade_ex-0.0.2.dist-info/WHEEL
mjade_ex-0.0.2.dist-info/top_level.txt
mjade_ex-0.0.2.dist-info/RECORD
