Metadata-Version: 2.1
Name: mjade-ex
Version: 0.0.2
Summary: KNUE_TEST
Home-page: https://github.com/cjo1784/mJade_class
Author: jinWoo
Author-email: cjo1784@gmail.com
Classifier: Programming Language :: Python :: 3
Classifier: License :: OSI Approved :: MIT License
Classifier: Operating System :: OS Independent
Requires-Python: >=3.6
License-File: LICENSE
